{
  "person_id": 30859,
  "handle": "tzvikafoghel",
  "tweets": [
    {
      "date": "2026-06-24T10:41:40+00:00",
      "text": "מוחמד ברכה כבר עבר מהוועדה לביטחון לאומי לחדרי החקירות במשטרה. \nעכשיו תורו של מנסור עבאס. https://t.co/is2qLAtHkc",
      "url": "https://x.com/tzvikafoghel/status/2069732684788641934",
      "likes": 65,
      "retweets": 11
    },
    {
      "date": "2026-06-23T18:14:08+00:00",
      "text": "RT @C14_news: חדשות 14 | אחרי החשיפה במהדורה: סערת הוועידה שבה השתתף מנסור עבאס לצד בכירי חמאס בטורקיה הגיעה לוועדה לביטחון לאומי, יו\"ר הוועדה ח\"כ פוגל הגיש תלונה במשטרה נגד יו\"ר רע\"מ\n\n#החדשות\n@MaggieTabibi @HaimOmri https://t.co/nAiggocV4p",
      "url": "https://x.com/tzvikafoghel/status/2069484165146333237",
      "likes": 0,
      "retweets": 25
    },
    {
      "date": "2026-06-22T16:07:30+00:00",
      "text": "יאיר והדמוקרטים, עוצמה יהודית כאן להרוס לכם את החגיגות. https://t.co/1XiGt82SFS",
      "url": "https://x.com/tzvikafoghel/status/2069089909525053791",
      "likes": 95,
      "retweets": 21
    },
    {
      "date": "2026-06-22T09:01:07+00:00",
      "text": "מרוב חלומות באנגלית, יש מי ששכח שבשכונה שלנו מדברים ערבית. https://t.co/nAHeehLlbB",
      "url": "https://x.com/tzvikafoghel/status/2068982606587175119",
      "likes": 50,
      "retweets": 8
    },
    {
      "date": "2026-06-21T17:14:19+00:00",
      "text": "מנסור, מחר תפגוש עוצמה יהודית, מזה לא תוכל להתחמק. https://t.co/rGoCRb1nK4",
      "url": "https://x.com/tzvikafoghel/status/2068744334703309263",
      "likes": 104,
      "retweets": 21
    },
    {
      "date": "2026-06-16T07:25:27+00:00",
      "text": "מאחורי המדים ניצב אדם המגן על המדינה, ומאחורי כל לובש מדים מאוים חייבת להתייצב המדינה כולה.\nאריה דורון, תמשיך לעשות את עבודתך בנאמנות וללא מורא. אנחנו נסתפק בעין אחת כדי לפקח על ״מזהה התהליכים״ וחבורתו.",
      "url": "https://x.com/tzvikafoghel/status/2066784201895014479",
      "likes": 48,
      "retweets": 6
    },
    {
      "date": "2026-06-11T17:37:21+00:00",
      "text": "בלי עוצמה יהודית, הימין מנהל מציאות במקום לשנות אותה. https://t.co/VlOVsVqRfh",
      "url": "https://x.com/tzvikafoghel/status/2065126251891683622",
      "likes": 14,
      "retweets": 2
    },
    {
      "date": "2026-06-10T14:14:53+00:00",
      "text": "בקלפי בוחרים ממשלה, לא פקידים! https://t.co/JloONAVALb",
      "url": "https://x.com/tzvikafoghel/status/2064712913999343630",
      "likes": 164,
      "retweets": 39
    },
    {
      "date": "2026-06-09T16:02:13+00:00",
      "text": "הביקור היחיד שיקבלו המחבלים הוא עם חבל התלייה. https://t.co/HoF1tZTGKG",
      "url": "https://x.com/tzvikafoghel/status/2064377537497567534",
      "likes": 39,
      "retweets": 6
    },
    {
      "date": "2026-06-04T12:11:50+00:00",
      "text": "https://t.co/yL3R482Uzr",
      "url": "https://x.com/tzvikafoghel/status/2062507620087271475",
      "likes": 186,
      "retweets": 34
    },
    {
      "date": "2026-06-04T09:42:51+00:00",
      "text": "מול הטרור צריך לבוא עם דחפורים, לא עם ניירת. https://t.co/orekFmDN6M",
      "url": "https://x.com/tzvikafoghel/status/2062470126142722169",
      "likes": 30,
      "retweets": 2
    },
    {
      "date": "2026-06-03T15:51:25+00:00",
      "text": "תם העידן שהשמאל ממנה את הבכירים. ראבילו, בהצלחה!",
      "url": "https://x.com/tzvikafoghel/status/2062200492785008957",
      "likes": 159,
      "retweets": 9
    },
    {
      "date": "2026-06-02T17:37:37+00:00",
      "text": "מנסור, אתה והמסגדים חלק מהמאבק שלנו בטרור. את כולכם נשתיק. https://t.co/lq5OB4CarG",
      "url": "https://x.com/tzvikafoghel/status/2061864829938237454",
      "likes": 21,
      "retweets": 5
    },
    {
      "date": "2026-05-28T13:13:11+00:00",
      "text": "RT @itamarbengvir: שיאני החקיקה !!! 🇮🇱🇮🇱🇮🇱\n\n*להלן רשימת החוקים שעוצמה יהודית הכניסה לספר החוקים של מדינת ישראל בכנסת האחרונה:*\n\n1. עונש מוות למחבלים \n2. פרוטקשן\n3. חוק המאבק בכלי הנשק הבלתי חוקיים \n4. החמרת ענישה על עבירות מין על רקע לאומני \n5. ⁠גירוש מסתננים \n6. ⁠החמרת ענישה על תקיפת לוחם כליאה \n7. ⁠חוק סיוע לבני משפחות של נעדרים \n8. ⁠מלחמה בסייעני השב״חים\n9. ⁠חוק המונע ממחבלים להגיע לדיונים בבית המשפט\n10. קבורה ממלכתית ללוחמי האש וללוחמי הכליאה \n11. ⁠רישיון נשק לפצועי צה״ל \n12. ⁠סמכויות ללוחמי הכליאה\n13. ⁠צווי הגבלה מנהליים כנגד ארגוני פשיעה (הרחקות)\n14. ⁠איסור העסקת תומכי טרור במוסדות לימודים ושלילית הטבות מהמוסדות \n15. ⁠הטבות למשפחות חיילים שנספו במערכה \n16. ⁠תשלומים לחטופים \n17. ⁠חוק המאבק בגניבות מבסיסי צה״ל \n18. ⁠איסור השטת כלי שיט בשכרות \n19. ⁠מחבלים קטינים בכלא במקום במעון נעול\n20. ⁠תגמולים למשרתי מילואים\n21. הקלות בקבלה ללימודים למילואימניקים\n22. ⁠הפסקת פעילות אונר״א \n23. ⁠ הרחקת מורשע בעבירת טרור מסביבת נפגע העבירה \n24. ⁠הרחקת מורשע בעבירות מין מסביבת נפגע העבירה (תיקון הצורך בנזק נפשי \"של ממש\" להוכחה)\n25. ⁠מעשה סדום יוגדר כמעשה אונס\n26. ⁠תיקון חוק ההתנתקות - חזרה לצפון השומרון' חומש, שאנור גנים וכדים.\n\nלמענכם ובשבילכם!\n\n@tzvikafoghel @limor_sonhrmelh @Eliyahu_a @Yitzik_kroizer @ItshakWaserlauf",
      "url": "https://x.com/tzvikafoghel/status/2059986344370139396",
      "likes": 0,
      "retweets": 83
    },
    {
      "date": "2026-05-26T17:17:00+00:00",
      "text": "לא תאמינו, זה לא בעזה, זה כאן בנגב. חברי כנסת, שותפי בנט ויאיר גולן, בנאומי שנאה והסתה. אני מזמין את כל הח״כים שעדיין מתלבטים ולפני שיהיה מאוחר מדי, להצטרף אליי להוציא את רע״מ מחוץ לחוק. https://t.co/U4zfffHL5m",
      "url": "https://x.com/tzvikafoghel/status/2059322926797598990",
      "likes": 129,
      "retweets": 19
    },
    {
      "date": "2026-05-24T15:26:39+00:00",
      "text": "שמור אותי מנשיאיי, ומאויביי אשמר בעצמי. \nמי שרואה בעמו בהמות, איבד את הזכות המוסרית להיות להם לנשיא.",
      "url": "https://x.com/tzvikafoghel/status/2058570379610689816",
      "likes": 655,
      "retweets": 67
    },
    {
      "date": "2026-05-21T07:58:53+00:00",
      "text": "הדרך למימוש הריבונות עוברת דרך הר הבית 🇮🇱\nחג שבועות שמח! 🌾 https://t.co/N7vzh5ocL5",
      "url": "https://x.com/tzvikafoghel/status/2057370532106887253",
      "likes": 256,
      "retweets": 34
    },
    {
      "date": "2026-05-19T04:00:07+00:00",
      "text": "שוטרי ישראל נלחמים בפשיעה ובטרור, אבל היועמ״שית משאירה אותם לבד מול תביעות אישיות על פעולות שביצעו במסגרת תפקידם. כששוטר מתלבט אם לפעול מחשש שייתבע אישית, ביטחון הציבור כולו נפגע. מאחר והיועמ״שית מסרה שלא תגיע גם היום לועדה, הדיון בוטל. הבג״ץ בדרך",
      "url": "https://x.com/tzvikafoghel/status/2056585666390000045",
      "likes": 126,
      "retweets": 18
    },
    {
      "date": "2026-05-18T06:47:31+00:00",
      "text": "התכוונתי לנהל היום דיון על חופש הביטוי במרחב הדמוקרטי. אבל נראה שהנושא לא מעניין את היועמ״שית ופרקליט המדינה, שהודיעו כי לא יגיעו לדיון.\nאי לכך, הדיון היום מבוטל ובכוונתי לפנות לבג״ץ בנושא.",
      "url": "https://x.com/tzvikafoghel/status/2056265407237947859",
      "likes": 361,
      "retweets": 54
    },
    {
      "date": "2026-05-15T11:29:40+00:00",
      "text": "בזמן שחיילי צה״ל נלחמים בכל הזירות, כשחיילים ואזרחים נפגעים, השותפים העתידיים של בנט, לפיד ויאיר גולן יושבים בכנסי פת״ח לצד תומכי טרור, רוצחים עטופים בדגלי פלסטין. אני אמשיך לרדוף אתכם במליאת הכנסת ובוועדות עד שנשלח אתכם הביתה. https://t.co/L07YqYxja8",
      "url": "https://x.com/tzvikafoghel/status/2055249249911136716",
      "likes": 52,
      "retweets": 10
    },
    {
      "date": "2026-05-14T13:59:50+00:00",
      "text": "🇮🇱 https://t.co/s6W1Cin3qT",
      "url": "https://x.com/tzvikafoghel/status/2054924653521494175",
      "likes": 18,
      "retweets": 1
    },
    {
      "date": "2026-05-11T05:50:47+00:00",
      "text": "לא צריך לראות טנקים ברחובות כדי לזהות דיקטטורה משפטית! \nבבוקר גלי בהרב מנסה לסכל מינוי של ראש מוסד, בערב מהלכת אימים על ערוץ 14. \nאני לא אשתוק. בשבוע הבא אקיים דיון בוועדה לביטחון לאומי, על חופש הביטוי של התקשורת.",
      "url": "https://x.com/tzvikafoghel/status/2053714415363543380",
      "likes": 534,
      "retweets": 85
    },
    {
      "date": "2026-05-06T12:47:43+00:00",
      "text": "תעדכנו את יאיר גולן ובנט שאני גומר להם את השותפים. https://t.co/gDMCNLFEcx",
      "url": "https://x.com/tzvikafoghel/status/2052007400798933031",
      "likes": 232,
      "retweets": 35
    },
    {
      "date": "2026-05-05T05:02:07+00:00",
      "text": "זחאלקה, אחרי סינוואר ונסראללה, אל תבחן את נחישותי לעצור את הטבח הבא. https://t.co/RQ5W5KYjFY",
      "url": "https://x.com/tzvikafoghel/status/2051527839644561630",
      "likes": 42,
      "retweets": 4
    },
    {
      "date": "2026-04-26T14:40:21+00:00",
      "text": "זה לא איחוד זה מיחזור 🗑️ https://t.co/QEQzB9FDHi",
      "url": "https://x.com/tzvikafoghel/status/2048411869451305140",
      "likes": 360,
      "retweets": 42
    },
    {
      "date": "2026-04-23T10:34:29+00:00",
      "text": "מכבסת קפלן בהנהלת גלי ועמית פתוחה 24/7 https://t.co/g45PsrmQRt",
      "url": "https://x.com/tzvikafoghel/status/2047262830039036118",
      "likes": 118,
      "retweets": 11
    },
    {
      "date": "2026-04-15T09:31:38+00:00",
      "text": "סופה של הדיקטטורה המשפטית ושלטון הגלימות מתחיל היום. https://t.co/biBQskBQye",
      "url": "https://x.com/tzvikafoghel/status/2044347910750408885",
      "likes": 52,
      "retweets": 7
    },
    {
      "date": "2026-04-12T22:38:28+00:00",
      "text": "Mr. President, just as you consider what is best for the United States, I consider what is best for the State of Israel-and that is the only thing before my eyes. My intention in voicing criticism was to be heard, and it succeeded in reaching the right ears. However, there was no intention to offend or show any disrespect, and for that I regret. I hold great respect and appreciation for our partners, with you at the forefront. It is important that we continue on this path until victory.\n\nכבוד הנשיא, כפי שאתה חושב על טובת ארה״ב כך גם אני חושב על טובת מדינת ישראל - והיא היחידה שעומדת לנגד עיני! כוונת הביקורת שלי הייתה להישמע, וזה הצליח והגיע לאוזניים הנכונות. אך לא הייתה כוונה לפגוע או לזלזל ועל כך אני מצר. אני חולק כבוד רב והערכה לשותפים שלנו, ואתה בראשם. וחשוב שנמשיך בדרך הזו עד לניצחון.",
      "url": "https://x.com/tzvikafoghel/status/2043458761071722628",
      "likes": 64,
      "retweets": 9
    },
    {
      "date": "2026-04-06T11:14:26+00:00",
      "text": "אני מגן על ביטחונם של אזרחי מדינת ישראל.\nגלעד קריב וחבריו ממהרים להגן על מחבלים.\nעם ישראל יודע מי עומד לצידו https://t.co/oaCc21B9qT",
      "url": "https://x.com/tzvikafoghel/status/2041112290422817128",
      "likes": 89,
      "retweets": 16
    },
    {
      "date": "2026-04-06T09:10:20+00:00",
      "text": "״זה לא יחול על הנוח׳בות״, ״השופטים ימנעו את העונש״ - כל התשובות למבול השטויות ששמעתם נמצא במדריך לחוק עונש מוות למחבלים. \nכנסו עכשיו.\n\nhttps://t.co/zutROQQhwA",
      "url": "https://x.com/tzvikafoghel/status/2041081056615350565",
      "likes": 226,
      "retweets": 26
    },
    {
      "date": "2026-04-01T07:59:44+00:00",
      "text": "הבטחנו וקיימנו. יצאנו מקונספציה ליצירתיות. עשינו היסטוריה. חג שמח! https://t.co/Y4rhRiq05Q",
      "url": "https://x.com/tzvikafoghel/status/2039251350454768114",
      "likes": 16,
      "retweets": 1
    },
    {
      "date": "2026-03-31T12:50:26+00:00",
      "text": "אין פלא שהשמאל מבולבל, הוא שבוי בידי פרשנים שמדברים שטויות. https://t.co/yHriGlX6bO",
      "url": "https://x.com/tzvikafoghel/status/2038962123330482209",
      "likes": 102,
      "retweets": 10
    },
    {
      "date": "2026-03-30T08:09:18+00:00",
      "text": "ההיסטוריה תשפוט את חברי הכנסת שיעמדו היום לצד רוצחי תינוקות. https://t.co/HbOc4acbqI",
      "url": "https://x.com/tzvikafoghel/status/2038528982191116415",
      "likes": 81,
      "retweets": 9
    },
    {
      "date": "2026-03-26T17:35:08+00:00",
      "text": "ביום שני נגלה מי מעדיף את קולות הערבים ומי את ביטחונה של מדינת ישראל. https://t.co/FYNYwbBV9V",
      "url": "https://x.com/tzvikafoghel/status/2037221827970273683",
      "likes": 77,
      "retweets": 11
    },
    {
      "date": "2026-03-25T17:02:36+00:00",
      "text": "השמאל וטיבי מציגים: רוח גבית למחבלים https://t.co/jpBTei3pz8",
      "url": "https://x.com/tzvikafoghel/status/2036851252936548580",
      "likes": 196,
      "retweets": 46
    },
    {
      "date": "2026-03-24T21:10:58+00:00",
      "text": "צעד נוסף בדרך לצדק היסטורי. https://t.co/QTtFXDvoXh",
      "url": "https://x.com/tzvikafoghel/status/2036551368358449547",
      "likes": 41,
      "retweets": 5
    },
    {
      "date": "2026-03-20T10:42:29+00:00",
      "text": "רמדאן.\nמלחמה.\nמדיניות השר. \nשקט מופתי. \nעוצמה יהודית.",
      "url": "https://x.com/tzvikafoghel/status/2034943656004583542",
      "likes": 69,
      "retweets": 6
    },
    {
      "date": "2026-03-18T17:43:20+00:00",
      "text": "בעבור מי שמתעסק בפוליטיקה זולה, כנראה שכשמדובר בעונש מוות למחבלים ישראל כבר לא ״ביתנו״. https://t.co/PynM150z5n",
      "url": "https://x.com/tzvikafoghel/status/2034324791109329074",
      "likes": 92,
      "retweets": 16
    },
    {
      "date": "2026-03-18T06:23:32+00:00",
      "text": "על זה נאמר - קפד ראשו!",
      "url": "https://x.com/tzvikafoghel/status/2034153713628037200",
      "likes": 23,
      "retweets": 5
    },
    {
      "date": "2026-03-17T13:14:24+00:00",
      "text": "החיסול הלילה הוא הוכחה ברורה: אין מחבל שחסין מהיד של מדינת ישראל. עכשיו הזמן להשלים את ההרתעה גם בתוך המדינה, עם חוק עונש מוות למחבלים. https://t.co/u7aTqawvf3",
      "url": "https://x.com/tzvikafoghel/status/2033894720963776893",
      "likes": 79,
      "retweets": 12
    },
    {
      "date": "2026-03-17T13:14:24+00:00",
      "text": "החיסול הלילה הוא הוכחה ברורה: אין מחבל שחסין מהיד של מדינת ישראל. עכשיו הזמן להשלים את ההרתעה גם בתוך המדינה, עם חוק עונש מוות למחבלים. https://t.co/u7aTqawvf3",
      "url": "https://x.com/tzvikafoghel/status/2033894720963776893",
      "likes": 79,
      "retweets": 12
    },
    {
      "date": "2026-03-15T18:20:36+00:00",
      "text": "מנהיגת השמאל היועמ״שית יורה לכל הכיוונים עם אקדח קפצונים. בשירות אסירי הנוח׳בות היא עושה הרבה רעש וכותרות בניסיון להפיל את השר לביטחון לאומי ונציב שב״ס. הם לא יצליחו אבל אולי ישבו יחד יום אחד. https://t.co/FNiRYNenoE",
      "url": "https://x.com/tzvikafoghel/status/2033247005464478001",
      "likes": 79,
      "retweets": 16
    },
    {
      "date": "2026-03-10T18:22:08+00:00",
      "text": "בקרוב… https://t.co/f7Weup159R",
      "url": "https://x.com/tzvikafoghel/status/2031435452830380184",
      "likes": 246,
      "retweets": 23
    },
    {
      "date": "2026-03-04T17:08:43+00:00",
      "text": "היועמ״שית המנותקת מוסיפה שמן למדורה שאיראן מנסה להצית בעורף שלנו. בזמן שאויבנו פועלים נגד ישראל מבחוץ, היועמ״שית בוחרת לפתוח חזית מבפנים נגד רצון הבוחר. גלי, אל תתבלבלי - את איראן נביס, את חיזבאללה נכריע, וכשנתפנה נחליף אותך. https://t.co/pXjaSuNbbX",
      "url": "https://x.com/tzvikafoghel/status/2029242648800776670",
      "likes": 447,
      "retweets": 75
    },
    {
      "date": "2026-03-03T12:38:05+00:00",
      "text": "https://t.co/wJXD3nSefk",
      "url": "https://x.com/tzvikafoghel/status/2028812153218642425",
      "likes": 23,
      "retweets": 2
    },
    {
      "date": "2026-02-28T16:14:30+00:00",
      "text": "כמי שהוביל מערכות יזומות בהפתעה באש, אני יודע לומר כי כשיש איום גרעיני ומוקדי טרור, אסור לנו לעמוד מנגד. היוזמה המשותפת והנחושה של ארה״ב וישראל מול איראן מגיעה לא רק כצעד של הגנה עצמית, אלא כמהלך קריטי להבטחת עתיד יציב ובטוח יותר לכולנו. הגיע הזמן שגם מדינות נוספות יתייצבו בצד שפועל להגנת הביטחון העולמי. \nאנחנו נמשיך לפעול להעצמת הביטחון הלאומי הישראלי 🇮🇱",
      "url": "https://x.com/tzvikafoghel/status/2027779451258372331",
      "likes": 23,
      "retweets": 1
    },
    {
      "date": "2026-02-27T09:08:51+00:00",
      "text": "את הרצח הבא אנחנו יכולים - וחייבים - למנוע עכשיו. https://t.co/ZRoAIxop8M",
      "url": "https://x.com/tzvikafoghel/status/2027309944987427279",
      "likes": 39,
      "retweets": 5
    },
    {
      "date": "2026-02-25T17:57:20+00:00",
      "text": "המסך האחרון שיראה המחבל לפני עונש המוות, יהיה מסך הזום. https://t.co/M4AiSy0FII",
      "url": "https://x.com/tzvikafoghel/status/2026718165971931180",
      "likes": 50,
      "retweets": 4
    },
    {
      "date": "2026-02-23T17:40:24+00:00",
      "text": "עונש מוות הוא המוצא היחיד של מחבלי הנוח׳בה מהתא בבתי הסוהר. https://t.co/p89Z6FJ4wG",
      "url": "https://x.com/tzvikafoghel/status/2025989131243856041",
      "likes": 344,
      "retweets": 34
    },
    {
      "date": "2026-02-19T09:26:28+00:00",
      "text": "בנט שרימה את בוחריו, קורא לבן גביר שמקיים את הבטחותיו, ״לא רציני״. תגיד נפתלי, מתי בפעם האחרונה הסתכלת במראה ולא קיבלת בחילה? https://t.co/sovNTob2cf",
      "url": "https://x.com/tzvikafoghel/status/2024415275471237339",
      "likes": 578,
      "retweets": 59
    },
    {
      "date": "2026-02-17T11:00:06+00:00",
      "text": "RT @itamarbengvir: היום! מחכה לראות אתכם ❤️ https://t.co/x3xe3BpXKU",
      "url": "https://x.com/tzvikafoghel/status/2023714063646130540",
      "likes": 0,
      "retweets": 39
    },
    {
      "date": "2026-02-11T18:13:27+00:00",
      "text": "RT @Eliyahu_a: כנגד אלה המכנים אותנו בבוז - ״מנשקי מזוזות ומשתטחי קברות הצדיקים״ - אנחנו משיבים בגאווה;\nכן! אלה אנחנו!\n\nכי בשאלה באיזה צד אנחנו,\nהצד של המתנכלים לדוכני תפילין,\nאו זה הנושא אותם בגאון,\n\nהצד של מחבקי המחבלים,\nאו זה המחמיר את תנאי כליאתם,\n\nהצד של המעלילים עלילות אונס על חיילינו,\nאו זה העוטף אותם בתמיכה ביודעו מי הם חייליו הצדיקים.\n\nהצד המתנצל על קיומנו בפני העולם,\nאו זה המרים ראש בגאווה יהודית.\n\nהצד שזועק נגד ״כיבוש״ בחברון ובשילה,\nאו זה הבונה ומחזק אותן.\n\nהתשובה ידועה.\nאנחנו בצד שלנו.\n\nהצד של ישראל.🇮🇱\n\nנתיבות.\n17/02. ערב ראש חודש אדר.\nאולמי פה פה.",
      "url": "https://x.com/tzvikafoghel/status/2021648795340341657",
      "likes": 0,
      "retweets": 36
    },
    {
      "date": "2026-02-11T12:18:24+00:00",
      "text": "גם 1000 תירוצים של נציגי הנוח’בות בכנסת ישראל לא ימנעו ממני לחוקק עונש מוות למחבלים. https://t.co/Vu16g1h7K4",
      "url": "https://x.com/tzvikafoghel/status/2021559440487637107",
      "likes": 358,
      "retweets": 41
    },
    {
      "date": "2026-02-10T18:21:00+00:00",
      "text": "RT @limor_sonhrmelh: בן גביר מגיע לנתיבות!\nתושבי נתיבות והסביבה, אנחנו מזמינים אתכם לכנס עוצמה יהודית.\nיום שלישי, 17.2, בשעה 19:00, באולמי פה פה בנתיבות. \nכולנו נהיה שם. \nתבואו, מחכים לכם 🇮🇱 https://t.co/AQQrAOdoYg",
      "url": "https://x.com/tzvikafoghel/status/2021288305480925551",
      "likes": 0,
      "retweets": 25
    },
    {
      "date": "2026-02-10T09:27:05+00:00",
      "text": "כל זמן שאני יו״ר הוועדה לביטחון לאומי ויו״ר סיעת עוצמה יהודית, לא אתן לאופוזיציה והשמאל להחריב את הביטחון הלאומי בשביל עוד כמה לייקים. https://t.co/9vSjDS6col",
      "url": "https://x.com/tzvikafoghel/status/2021153941543629122",
      "likes": 140,
      "retweets": 12
    },
    {
      "date": "2026-02-09T18:04:52+00:00",
      "text": "בן גביר מגיע לנתיבות!\nתושבי נתיבות והסביבה, אנחנו מזמינים אתכם לכנס עוצמה יהודית.\nיום שלישי, 17.2, בשעה 19:00, באולמי פה פה בנתיבות. \nכולנו נהיה שם. \nתבואו, מחכים לכם 🇮🇱 https://t.co/SkGQ4ccMRY",
      "url": "https://x.com/tzvikafoghel/status/2020921856132567168",
      "likes": 169,
      "retweets": 20
    },
    {
      "date": "2026-02-09T17:09:46+00:00",
      "text": "אחרי ה - 07/10 זה צעד הכרחי! https://t.co/1OjkdD2gnJ",
      "url": "https://x.com/tzvikafoghel/status/2020907993307525213",
      "likes": 33,
      "retweets": 8
    },
    {
      "date": "2026-02-08T18:11:42+00:00",
      "text": "RT @Yitzik_kroizer: בן גביר מגיע לנתיבות!\nתושבי נתיבות והסביבה, אנחנו מזמינים אתכם לכנס עוצמה יהודית.\nיום שלישי, 17.2, בשעה 19:00, באולמי פה פה בנתיבות. \nכולנו נהיה שם. \nתבואו, מחכים לכם 🇮🇱 https://t.co/1Ip56Eawt9",
      "url": "https://x.com/tzvikafoghel/status/2020561188157813163",
      "likes": 0,
      "retweets": 17
    },
    {
      "date": "2026-02-07T18:03:17+00:00",
      "text": "RT @ItshakWaserlauf: בן גביר מגיע לנתיבות!\nתושבי נתיבות והסביבה ,\nאנחנו מזמינים אתכם לכנס עוצמה יהודית.\nיום שלישי, 17.2, בשעה 19:00, באולמי פה פה בנתיבות. \nכולנו נהיה שם. \nתבואו, מחכים לכם https://t.co/zqKWXs4PA6",
      "url": "https://x.com/tzvikafoghel/status/2020196684928807125",
      "likes": 0,
      "retweets": 23
    }
  ]
}