{"person_id": 468, "name": "ישראל כץ", "party": "הליכוד", "interviews": [{"video_id": "-eaGezy3huI", "url": "https://www.youtube.com/watch?v=-eaGezy3huI", "title": "שר הביטחון ישראל כץ: &quot;המלחמה לא תיעצר&quot; | ראיון עם יעקב ברדוגו", "channel": "ביבי השקרן", "published_at": "2026-06-19T09:33:57Z", "person_id": 468, "mk_name": "ישראל כץ", "duration_sec": 24.6, "engine": "ivrit-ai/whisper-large-v3-turbo-ct2", "transcribed_at": "2026-06-27T00:18:57.031913+00:00", "segments": [{"start": 0.14, "end": 7.2, "text": "קודם כל המלחמה לא תיעצר, אם זה... רגע, זה, לשם אני רוצה להגיע. קודם כל המלחמה לא תיעצר. לא תיעצר בלבנון, אתה יכול להסתכל רגע ולהגיד לנו,"}, {"start": 7.52, "end": 18.26, "text": "שר הביטחון, חד-משמעית, חד-משמעית. המלחמה לא תיעצר, למרות הלחצים האמריקאים, למרות הבקשות שלהם לגבי סלאמבד. עוד פעם, אנחנו מתואמים מהאמריקאים, המלחמה לא תיעצר."}, {"start": 18.64, "end": 24.44, "text": "600,000 תושבים שעזבו לשם הגנתם את דרום לבנון לא חוזרים מדרום לליטני."}]}, {"video_id": "iyy8UIOgh2s", "url": "https://www.youtube.com/watch?v=iyy8UIOgh2s", "title": "שר הביטחון כ”ץ: &quot;ראש הממשלה אמר: צריך לסכל את חמינאי. זה היה אמור להתבצע ביוני והוקדם לפברואר&quot;", "channel": "i24NEWS עברית", "published_at": "2026-03-05T19:51:06Z", "person_id": 468, "mk_name": "ישראל כץ", "duration_sec": 57.7, "engine": "ivrit-ai/whisper-large-v3-turbo-ct2", "transcribed_at": "2026-06-27T00:19:02.111266+00:00", "segments": [{"start": 0.3, "end": 7.4, "text": "התובנה שהניח ראש הממשלה אמר צריך להסתכל איתך מן האי וכולנו, אני כשר ביטחון, צה״ל, הגורמים התחלנו להיערך"}, {"start": 8.32, "end": 16.76, "text": "לקראת ביצוע היעד הזה באמצע השנה ואז פרצו המהומות בתוך איראן וזה שינה את המצב בשני ממדים."}, {"start": 17.84, "end": 28.52, "text": "מצד אחד זה הראה שיש כאן אפשרות להביא לשינוי המשטר באיראן בגלל הרצון של האנשים ומצד שני זה הגביר את הסכנה בתקיפת מנע והחלטנו להקדים לפברואר"}, {"start": 29.02, "end": 32.12, "text": "את הדבר הזה. וכאן ראש הממשלה עשה דבר"}, {"start": 32.94, "end": 36.08, "text": "שלא מכיר הרבה מנהיגים בעולם, אולי אף אחד לא יכול לעשות,"}, {"start": 36.96, "end": 38.96, "text": "ליצור שותפות עם נשיא ארצות הברית."}, {"start": 39.7, "end": 42.16, "text": "אומרים, זה השפיע על זה, זה השפיע על זה, הם החליטו על זה ביחד."}, {"start": 42.64, "end": 47.62, "text": "עם בניית היכולות בסופו של דבר לקבלת ההחלטה המשותפת ולהקדמתה,"}, {"start": 48.04, "end": 50.16, "text": "וזה כבר לפי נסיבות, ממוצאי שבת"}, {"start": 51.0, "end": 53.88, "text": "ושבת בבוקר עקב מידע מודיעיני שאירע על ההתכנסות."}]}, {"video_id": "8Q0IdisBa44", "url": "https://www.youtube.com/watch?v=8Q0IdisBa44", "title": "שר הביטחון כ&quot;ץ: חיסול חמינאי תוכנן מנובמבר, צה&quot;ל יישאר בעזה ובלבנון", "channel": "חדשות 13", "published_at": "2026-03-05T18:52:47Z", "person_id": 468, "mk_name": "ישראל כץ", "duration_sec": 429.2, "engine": "ivrit-ai/whisper-large-v3-turbo-ct2", "transcribed_at": "2026-06-27T00:19:27.789984+00:00", "segments": [{"start": 0.9, "end": 11.4, "text": "שר הביטחון ישראל כץ, שלום. שלום. לפני כמה חודשים, בסוף חודש יוני, ישבנו כאן, אתה על הכיסא הזה, ושאלתי אותך בכמה השגנו לאחור את תוכנית הגרעין ותוכנית הטילים הבליסטיים."}, {"start": 11.82, "end": 13.72, "text": "ענית שבשנים ארוכות אחורה."}, {"start": 14.08, "end": 14.4, "text": "טעית?"}, {"start": 15.34, "end": 19.74, "text": "ממש לא. אנחנו סיכלנו את תוכנית הגרעין האיראנית במבצע עם כלביא."}, {"start": 20.64, "end": 26.54, "text": "ופגענו בצורה עצימה וקשה מאוד במערך ייצור הטילים הבליסטיים של איראן,"}, {"start": 27.52, "end": 47.6, "text": "ואנחנו היינו צריכים לוודא מראש שהם לא יחזרו, ינסו לחזור לדבר הזה. רגע, אז ההכרזות שלכם, של ראש הממשלה, שלך, על ניצחון לדורות, הן נכונות לגמרי. בחודש יוני, ניצחון לדורות שמחזיק שמונה חודשים. אזרחי ישראל לא חשבו, הוא לא מחזיק שמונה חודשים. אזרחי ישראל לא חשבו שכעבור שמונה חודשים הם שוב יהיו נתונים לירי טילים מאיראן."}, {"start": 48.76, "end": 52.38, "text": "עוד פעם, גם בסוף אותה מערכה נשארו לאיראן טילים."}, {"start": 53.74, "end": 55.92, "text": "פגענו במערכות ייצור הטילים שלה,"}, {"start": 56.14, "end": 61.74, "text": "ואנחנו סיכמנו את תוכנית הגריל. המטרה העיקרית הייתה לסכל את איום ההשמדה"}, {"start": 62.56, "end": 65.5, "text": "מעל מדינת ישראל, שהיה קרוב מאוד. הם פיתחו תוכנית"}, {"start": 66.12, "end": 67.26, "text": "שהייתה קרובה להבשלה."}, {"start": 67.76, "end": 73.08, "text": "אתה עכשיו יכול להבטיח לאזרחי ישראל שבתום המערכה... רגע, אני רוצה לחזור לליבת העניין. אוקיי."}, {"start": 73.52, "end": 75.2, "text": "ובא ראש הממשלה בחודש נובמבר,"}, {"start": 76.34, "end": 77.48, "text": "ואמר שהוא הגיע למסקנה"}, {"start": 78.86, "end": 80.86, "text": "שבלי לחסל את חמינאי,"}, {"start": 82.4, "end": 84.28, "text": "לא נוכל להוריד את"}, {"start": 85.06, "end": 89.44, "text": "החזרתיות של איראן לנסות לחזור למקומות האלה. את זה הוא אומר למי בחודש נובמבר?"}, {"start": 90.46, "end": 93.38, "text": "הוא אומר לי ולפורום מאוד מצומצם. בדיונים פה. לרמטכ״ל."}, {"start": 94.8, "end": 97.88, "text": "ולכן התחלנו לבנות תוכנית"}, {"start": 99.16, "end": 103.38, "text": "שמועד להבשלה שלה היה אמור להיות באמצע השנה הזאת, במאי, יוני."}, {"start": 103.74, "end": 106.26, "text": "למה זה מוקדם? פרצו המהומות"}, {"start": 106.76, "end": 107.44, "text": "בתוך איראן,"}, {"start": 108.34, "end": 109.34, "text": "והם גרמו לשני דברים."}, {"start": 110.48, "end": 111.78, "text": "מצד אחד הם יצרו כאן הזדמנות"}, {"start": 112.68, "end": 115.0, "text": "שהעם האיראני רוצה להפיל את המשטר."}, {"start": 116.52, "end": 125.08, "text": "מצד שני הם הגבירו מאוד את הסכנה למכה מקדימה איראנית על מדינת ישראל ועל הכוחות האמריקאים באזור. הם הכינו תוכנית."}, {"start": 125.56, "end": 126.86, "text": "ואז היה כאן תהליך"}, {"start": 127.78, "end": 129.08, "text": "שהוא השתנה מעת לעת."}, {"start": 130.28, "end": 132.6, "text": "בסוף הוחלט לפעול במוצאי שבת,"}, {"start": 133.32, "end": 134.82, "text": "אבל אז הגיע המידע לפגישה בבוקר."}, {"start": 136.24, "end": 139.02, "text": "חמינאי הוא היה יעד בכל מקרה במתחם שלו."}, {"start": 140.06, "end": 141.72, "text": "ואז בעצם המבצע יצא לדרך,"}, {"start": 141.8, "end": 151.76, "text": "והתוצאות שלו היו מדהימות. נכון הדיווח בניו יורק טיימס, שבאמצע ינואר טראמפ כבר אמור היה לתקוף, ונתניהו התקשר וביקש ממנו להמתין עם התקיפה,"}, {"start": 152.16, "end": 156.1, "text": "כי ישראל עדיין לא ערוכה מספיק לאפשרות שאיראן תתקוף אותה."}, {"start": 156.88, "end": 161.38, "text": "אני לא מתייחס לדיווחים כאלה ואחרים. התיאום היה מלא, והוא הבשיל."}, {"start": 161.98, "end": 166.42, "text": "עכשיו, מעבר לסיכול חמינאי, המערכה התרחבה, היעדים התרחבו."}, {"start": 166.82, "end": 168.72, "text": "ובעצם להביא למצב,"}, {"start": 169.48, "end": 171.96, "text": "וזאת תוצאה נלווית שאנחנו שואפים לה."}, {"start": 172.78, "end": 181.1, "text": "וזה שהעם האיראני יקבל את התנאים להפיל את המשטר הזה. אני רוצה רק לחדד את העניין של ההבטחות שניתנו אז לעומת ההבטחות שניתנות היום."}, {"start": 181.58, "end": 198.18, "text": "האם אתה יכול להבטיח לאזרחי ישראל שבתום המערכה הזו אין יותר סבבים מול איראן בטווח הנראה לעין, או שכמו אל מול אויבים אחרים שלנו, גם מול האיראנים אנחנו נכנסים למערכה שיכול להיות שנראה מעת לעת,"}, {"start": 198.32, "end": 200.06, "text": "אחת לכמה חודשים, אולי אחת לשנה,"}, {"start": 200.5, "end": 204.52, "text": "סבבים בהיקפיים ובעוצמות שאנחנו רואים? אני לא נכנס להגדרות מוחלטות."}, {"start": 205.46, "end": 215.26, "text": "אי אפשר בחיים האלה ובמציאות להיכנס להגדרות מוחלטות. כבר לקח ראשון ממבצעי תל אביב. לגבות עם תל אביב, מה שאמרתי הוא תקף לחלוטין. אני שואלת שאלה אחרת. האם יש לנו תוכנית סדורה,"}, {"start": 215.82, "end": 223.22, "text": "איך נראים הצעדים הבאים שאינם רק צבאיים על מנת להוביל להפלת המשטר? כי כמו שאתה יודע, משטר נופל גם,"}, {"start": 223.76, "end": 226.32, "text": "או לא רק, בעקבות מהלכים צבאיים."}, {"start": 228.2, "end": 229.34, "text": "עניינת שהיא זו שתוביל?"}, {"start": 230.28, "end": 232.28, "text": "אני עוד פעם, אני לא אכנס לכל הדברים האלה."}, {"start": 233.54, "end": 235.06, "text": "הדבר העיקרי, כמו שאני אומר,"}, {"start": 235.4, "end": 238.12, "text": "שמשנה שם את המציאות, זה המהלומות שמרסקות"}, {"start": 238.72, "end": 241.58, "text": "את תשתיות ואת בני המשטר האיראני ואת יכולותיו."}, {"start": 242.12, "end": 246.84, "text": "אז רק אתמול שמענו על התחלה של התארגנות של מיליציות כורדיות."}, {"start": 247.34, "end": 255.22, "text": "אנחנו עומדים בקשר? ישראל עומדת בקשר עם... כל יום תשמעי על משהו אחר. בסופו של דבר, רוב העם האיראני, וזה בדוק, 80 אחוז,"}, {"start": 256.08, "end": 257.12, "text": "לא רוצים במשטר הזה."}, {"start": 257.74, "end": 260.24, "text": "הם הפגינו, ואז הם דוכאו באכזריות"}, {"start": 260.9, "end": 262.6, "text": "רצחנית ומה שקרה."}, {"start": 263.54, "end": 267.62, "text": "ואז הם פנו לעזרה. עכשיו בעצם הם מקבלים, אנחנו, מהשיקולים שלנו, פועלים"}, {"start": 268.32, "end": 271.18, "text": "עם האמריקאים, וזה אמור לסייע להם בצורה דרמטית"}, {"start": 271.76, "end": 282.32, "text": "להפסיק את המטרות לכולם ביחד. אוקיי, בואו ננסה, למשל, יש דיווחים על כך שארצות הברית וישראל מחמשות גורמי אופוזיציה באיראן ומיליציות,"}, {"start": 282.86, "end": 284.26, "text": "מתנגדות משטר."}, {"start": 284.9, "end": 286.94, "text": "אלו פעולות שאנחנו נוקטים על מנת להוביל..."}, {"start": 287.26, "end": 290.02, "text": "פירוט פרטים מבצעיים, ואני לא אכנס לדברים האלה."}, {"start": 290.8, "end": 293.06, "text": "באופן כללי, אני אומר מה המהלך המרכזי,"}, {"start": 293.22, "end": 297.42, "text": "וכולם עושים את כל מה שצריך ואפשר כדי לקדם את המטרה."}, {"start": 297.74, "end": 299.24, "text": "ואם זה יקרה, ולזה אנחנו מקווים,"}, {"start": 299.78, "end": 301.2, "text": "אז השינוי יהיה דרמטי."}, {"start": 301.62, "end": 305.56, "text": "תוך כמה זמן. עם העם האיראני, אגב, בניגוד להסכמי שלום שחתמנו פה-שם,"}, {"start": 306.16, "end": 314.82, "text": "זה היה יותר עם המשטר מאשר עם העם. פה זה הפוך. העם הוא הרבה יותר בנוי לקשר עם ישראל ועם החברה הישראלית,"}, {"start": 315.4, "end": 317.68, "text": "ולכן אנחנו נסתכל, אם זה יקרה,"}, {"start": 318.2, "end": 320.7, "text": "לא רק שמסלקים איום, אלא אנחנו גם נבנה גם,"}, {"start": 321.2, "end": 324.26, "text": "איך אומרים, מועמדת פוטנציאלית להסכמי אברהם החדשים,"}, {"start": 325.04, "end": 333.02, "text": "או דברים מהסוג הזה. אבל להבטיח בדייקנות שאנחנו אלה שנחליף משטר, אנחנו לא יכולים להגיד את הדבר הזה. כלומר, אם לא ישתנה המשטר,"}, {"start": 333.5, "end": 336.36, "text": "המשמעות עבור אזרחי ישראל, וזה דבר שחשוב לשקף,"}, {"start": 336.8, "end": 343.26, "text": "זה שאנחנו נהיה בסבבים כאלה מול אירן אחת לתקופה. ממש לא. לא סבבים כאלה. מה שאנחנו עכשיו עושים,"}, {"start": 344.04, "end": 347.06, "text": "אנחנו מרסקים את תשתיות המשטר הזה."}, {"start": 347.44, "end": 349.32, "text": "אני רוצה להספיק איתך שאלה אחרונה."}, {"start": 349.7, "end": 354.48, "text": "אנחנו מדברים על איראן ועל ההישגים, ואכן יש הישגים בזירה האיראנית, אבל מתנהלת פה עוד מערכה,"}, {"start": 354.7, "end": 356.72, "text": "המערכה שממנה הכול התחיל,"}, {"start": 357.14, "end": 369.1, "text": "הזירה שממנה הכול התחיל, עזה. אתם הבטחתם במשך שנתיים וחצי שחמאס לא ישלוט יותר בעזה. זה מה שיהיה. דה פקטו, רגע. דה פקטו, חמאס היום מתעצם. זה מה שיהיה. זה מה שיהיה, אבל זה לא מה שקורה עכשיו."}, {"start": 369.54, "end": 372.84, "text": "האם נכשלתם בעזה? תלמדו להאמין למה שאנחנו אומרים."}, {"start": 373.54, "end": 386.78, "text": "אנחנו רוצים, אבל אני מסתכלת על המציאות. אמרנו על איראן, וזה קורה באיראן. שר הביטחון, אני מסתכלת על המציאות, והמציאות היא שהיום בעזה יש חמאס שהולך ומתעצם מאז הסכם הפסקת האש באוקטובר. יש חמאס על תנאי, ישראל נמצאת ברוב השטח. אבל יש חמאס."}, {"start": 387.72, "end": 390.68, "text": "ישראל נמצאת ברוב השטח של עזה. עשינו את כל החטופים,"}, {"start": 392.02, "end": 394.6, "text": "ונשארנו ברוב השטח, אף אחד לא חלם שזה יקרה."}, {"start": 395.04, "end": 395.94, "text": "ויש היום תהליך"}, {"start": 396.62, "end": 398.1, "text": "שבו צריך להתפרק מהנשק."}, {"start": 398.46, "end": 404.24, "text": "אתה יודע בדיוק כמוני שאף כוח רב-לאומי לא יפרז את עזה. בסדר, אז אנחנו נפרץ. אז מתי?"}, {"start": 405.0, "end": 419.12, "text": "מה הדדליין? אנשים רוצים לחזור לגור בגבולות. תגידי, עכשיו, כשאת רואה מה קורה באיראן, את לא מבינה שיש לנו מכלול שיקולים שאנחנו, אל תפחדים. אני מפחדת שאנחנו מסירים את העיניים מהזירה העזתית. לא נעזוב, שם הכול התחיל, לא יהיה שם חמאס שיאיים."}, {"start": 419.64, "end": 421.4, "text": "קודם כל, צה״ל תמיד יישאר בתוך עזה,"}, {"start": 422.12, "end": 425.12, "text": "בתוך לבנון. תמיד יישאר? כן, עם רצועת ביטחון."}, {"start": 425.88, "end": 427.6, "text": "שר הביטחון ישראל כץ, תודה רבה לך."}, {"start": 427.98, "end": 428.48, "text": "תודה רבה."}]}, {"video_id": "hmA8pkgfPhs", "url": "https://www.youtube.com/watch?v=hmA8pkgfPhs", "title": "נאום שר הביטחון ישראל כץ - כנס 50 שנה לרשות החברות הממשלתיות", "channel": "רשות החברות הממשלתיות", "published_at": "2026-02-11T15:01:19Z", "person_id": 468, "mk_name": "ישראל כץ", "duration_sec": 1153.1, "engine": "ivrit-ai/whisper-large-v3-turbo-ct2", "transcribed_at": "2026-06-27T00:20:21.138013+00:00", "segments": [{"start": 0.57, "end": 1.75, "text": "שלום לכולם,"}, {"start": 3.19, "end": 6.17, "text": "מנהל רשות החברות הממשלתיות רועי כחלון,"}, {"start": 7.49, "end": 9.67, "text": "מנכ״לי החברות הממשלתיות,"}, {"start": 11.53, "end": 12.21, "text": "יושבי-ראש,"}, {"start": 13.83, "end": 14.67, "text": "ועדי עובדים,"}, {"start": 16.31, "end": 17.41, "text": "חברי מועצות המנהלים,"}, {"start": 18.77, "end": 19.71, "text": "קהל נכבד ועצום,"}, {"start": 21.85, "end": 25.13, "text": "אני שמח להיות כאן במלאת 50 שנה"}, {"start": 26.45, "end": 28.45, "text": "להקמת רשות החברות הממשלתיות."}, {"start": 30.33, "end": 31.33, "text": "מאז שהוקמה"}, {"start": 33.07, "end": 35.01, "text": "פעילות הרשויות,"}, {"start": 36.09, "end": 39.31, "text": "החברות הממשלתיות התרחבה, פעילות הרשות התרחבה,"}, {"start": 41.03, "end": 46.13, "text": "ובהחלט היום החברות הממשלתיות מהוות גורם מאוד חשוב ומשמעותי"}, {"start": 48.29, "end": 49.01, "text": "בפיתוח המשק."}, {"start": 49.35, "end": 52.91, "text": "לאורך תפקידי הלא-מעטים בממשלה"}, {"start": 54.27, "end": 58.23, "text": "תמיד ליוויתי את עבודת החברות ותמיד"}, {"start": 58.23, "end": 62.01, "text": "הם שימשו לי כמנוף משמעותי לקידום מדיניות."}, {"start": 63.87, "end": 65.87, "text": "משרד החקלאות,"}, {"start": 67.03, "end": 69.99, "text": "עם חברות הייצוא החקלאי, שאז היו ממשלתיות,"}, {"start": 71.35, "end": 72.15, "text": "משרד התחבורה,"}, {"start": 74.03, "end": 76.81, "text": "על כל חברותיו למעלה מעשר שנים,"}, {"start": 79.41, "end": 80.29, "text": "משרד החוץ,"}, {"start": 81.79, "end": 84.67, "text": "היו גם גופים שקשורים,"}, {"start": 86.65, "end": 88.01, "text": "משרד האוצר כמובן,"}, {"start": 88.99, "end": 90.03, "text": "משרד האנרגיה,"}, {"start": 90.85, "end": 91.59, "text": "משרד הביטחון."}, {"start": 93.27, "end": 95.53, "text": "היום, במסגרת תפקידי כשר ביטחון,"}, {"start": 96.81, "end": 100.15, "text": "בהחלט אנחנו עובדים מול רשות החברות הממשלתיות,"}, {"start": 101.85, "end": 105.53, "text": "בצמוד למנכ״ל רשות החברות"}, {"start": 106.49, "end": 107.65, "text": "והגורמים האחרים,"}, {"start": 108.81, "end": 113.55, "text": "ובעיקר בכל מה שקשור לחברות הביטחוניות."}, {"start": 115.25, "end": 116.65, "text": "החברות הביטחוניות היום"}, {"start": 116.87, "end": 120.01, "text": "צועדות יד ביד"}, {"start": 120.75, "end": 122.43, "text": "עם המערכה, עם מלחמת התקומה,"}, {"start": 124.17, "end": 125.87, "text": "עם המלחמה בכל החזיתות."}, {"start": 127.13, "end": 129.13, "text": "החברות הביטחוניות הכשירו,"}, {"start": 129.83, "end": 130.23, "text": "פיתחו,"}, {"start": 130.91, "end": 131.33, "text": "ייצרו"}, {"start": 132.25, "end": 133.23, "text": "מערכות שלמות"}, {"start": 134.15, "end": 136.65, "text": "שאנחנו נשענים עליהן, צה״ל נשען עליהן,"}, {"start": 137.53, "end": 141.33, "text": "מערכת הביטחון נשענת עליהן בהשגת המשימות,"}, {"start": 142.71, "end": 143.79, "text": "בהשגת ביטחון,"}, {"start": 144.61, "end": 145.33, "text": "בהכרעה,"}, {"start": 145.89, "end": 146.55, "text": "בהגנה,"}, {"start": 147.23, "end": 148.17, "text": "ובכל שאר התחומים."}, {"start": 149.21, "end": 150.03, "text": "והעולם כולו,"}, {"start": 151.05, "end": 154.43, "text": "בשלב הזה, אחרי למעלה משנתיים של מערכה,"}, {"start": 155.73, "end": 156.05, "text": "עומד"}, {"start": 156.81, "end": 157.07, "text": "מביט"}, {"start": 158.03, "end": 161.23, "text": "ומשתאה נוכח היכולות של מדינת ישראל"}, {"start": 162.51, "end": 162.81, "text": "בתחומים"}, {"start": 164.77, "end": 169.43, "text": "שבהם אנחנו פועלים בהתקפה, בהגנה,"}, {"start": 169.95, "end": 172.09, "text": "בהשגת יעדים שונים."}, {"start": 173.35, "end": 173.95, "text": "הפיתוח,"}, {"start": 175.11, "end": 176.19, "text": "פיתוח ארוך השנים,"}, {"start": 176.81, "end": 177.35, "text": "האיכותי,"}, {"start": 178.53, "end": 179.59, "text": "מי שעוסק בדברים"}, {"start": 180.79, "end": 182.87, "text": "ועוסקים בקידום הדברים עצמם,"}, {"start": 183.83, "end": 186.19, "text": "הביאו את מדינת ישראל להיות בשורה הראשונה"}, {"start": 186.99, "end": 187.73, "text": "של היכולות,"}, {"start": 193.19, "end": 193.55, "text": "המערכות,"}, {"start": 194.43, "end": 197.31, "text": "של כל המערכות שאנחנו נשענים עליהן."}, {"start": 199.21, "end": 203.61, "text": "אנחנו נמצאים עכשיו בשלב מאוד משמעותי ומכריע,"}, {"start": 203.79, "end": 207.07, "text": "ביחד עם ראש הממשלה בנימין נתניהו."}, {"start": 208.31, "end": 210.63, "text": "אנחנו מקדמים תוכנית"}, {"start": 211.43, "end": 214.39, "text": "חסרת תקדים של תוספת עצומה"}, {"start": 215.89, "end": 217.21, "text": "לתקציב הביטחון"}, {"start": 218.41, "end": 219.29, "text": "בכל מה שקשור"}, {"start": 219.85, "end": 220.77, "text": "לבניית הכוח,"}, {"start": 221.55, "end": 222.27, "text": "לפיתוחו,"}, {"start": 222.91, "end": 223.63, "text": "למחקר,"}, {"start": 224.53, "end": 226.37, "text": "לפיתוח, לייצור,"}, {"start": 227.57, "end": 229.25, "text": "על רקע כל הלקחים"}, {"start": 230.45, "end": 232.85, "text": "שלמדנו ואנחנו לומדים מהמערכה האחרונה."}, {"start": 233.91, "end": 237.01, "text": "ועל רקע הרצון, להיות עצמאים ככל שניתן"}, {"start": 237.97, "end": 238.53, "text": "בייצור"}, {"start": 239.39, "end": 242.63, "text": "של המערכת הביטחונית במדינת ישראל,"}, {"start": 243.47, "end": 244.21, "text": "כדי לא להישען"}, {"start": 245.51, "end": 247.59, "text": "ככל שניתן על גורמים אחרים."}, {"start": 249.61, "end": 250.47, "text": "אנחנו החלטנו,"}, {"start": 251.51, "end": 253.77, "text": "ביחד גם עם שר האוצר,"}, {"start": 255.45, "end": 256.31, "text": "לקדם תוכנית"}, {"start": 257.65, "end": 263.41, "text": "של תוספת של 350 מיליארד שקלים לעשור הקרוב."}, {"start": 264.61, "end": 267.79, "text": "אם אני מתרגם את זה לשער הדולר ביום כזה או אחר,"}, {"start": 268.91, "end": 271.49, "text": "זה 100 מיליארד דולר תוספת,"}, {"start": 272.63, "end": 273.41, "text": "מעבר לתקציב הביטחון,"}, {"start": 275.07, "end": 276.75, "text": "שילכו, כמו שאמרתי,"}, {"start": 277.59, "end": 278.35, "text": "למחקר ופיתוח,"}, {"start": 279.47, "end": 280.43, "text": "לבניית הכוח,"}, {"start": 281.31, "end": 282.15, "text": "לפיתוח מערכות,"}, {"start": 282.75, "end": 283.91, "text": "להגדלת ההיקפים,"}, {"start": 284.91, "end": 286.23, "text": "לשיתופי פעולה עם מדינות,"}, {"start": 287.25, "end": 290.05, "text": "גם כן בתחום הייצור והפיתוח."}, {"start": 291.31, "end": 292.89, "text": "והדבר הזה יביא את ישראל"}, {"start": 294.49, "end": 294.71, "text": "למקום"}, {"start": 295.31, "end": 296.25, "text": "אחר לחלוטין."}, {"start": 297.33, "end": 298.73, "text": "החברות הממשלתיות,"}, {"start": 300.07, "end": 306.23, "text": "וביחד אתן גם חברות פרטיות לא מעטות שעובדות לצדן וביחד אתן,"}, {"start": 307.43, "end": 309.19, "text": "ייכנסו לתנופה חסרת תקדים"}, {"start": 310.33, "end": 311.09, "text": "בכל התחומים"}, {"start": 311.97, "end": 313.25, "text": "שהחברות עוסקות בהם"}, {"start": 313.87, "end": 314.83, "text": "ותעסוקנה בהם"}, {"start": 315.41, "end": 315.99, "text": "גם כן בעתיד."}, {"start": 319.17, "end": 319.97, "text": "התעשייה האווירית,"}, {"start": 322.13, "end": 323.45, "text": "רפאל, אלביט,"}, {"start": 324.23, "end": 325.35, "text": "שהיא לא חברה ממשלתית,"}, {"start": 326.39, "end": 327.05, "text": "חברה גדולה,"}, {"start": 328.07, "end": 330.45, "text": "ועוד חברות אחרות בתחום הפרטי,"}, {"start": 331.59, "end": 333.65, "text": "כולם ייכנסו לתהליך מואץ"}, {"start": 334.67, "end": 335.53, "text": "של הרחבה,"}, {"start": 336.29, "end": 336.99, "text": "של פיתוח,"}, {"start": 338.59, "end": 340.41, "text": "של שותפויות, כמו שאמרתי,"}, {"start": 341.33, "end": 341.99, "text": "ודברים אחרים."}, {"start": 342.71, "end": 347.47, "text": "על הפרק כרגע הנושא של הנפקה והפרטה של התעשייה האווירית,"}, {"start": 348.73, "end": 349.81, "text": "ובעודי אומר את זה,"}, {"start": 350.85, "end": 352.27, "text": "למרות האור המסנוור,"}, {"start": 352.43, "end": 356.15, "text": "אני בטוח שאני רואה כאן את יושב-ראש רפאל,"}, {"start": 356.55, "end": 357.71, "text": "בטח גם המנכ״ל כאן,"}, {"start": 358.45, "end": 360.11, "text": "שהוא כבר אומר, גם אנחנו רוצים."}, {"start": 361.75, "end": 363.93, "text": "אז בהחלט המדיניות"}, {"start": 364.71, "end": 370.29, "text": "היא מדיניות ברורה של לאפשר ולקדם את הנושא הזה,"}, {"start": 370.69, "end": 375.39, "text": "דבר שגם יקנה משאבים עצומים למדינת ישראל"}, {"start": 376.35, "end": 378.57, "text": "וגם יאפשר לחברה"}, {"start": 379.49, "end": 380.77, "text": "לפעול באופן יותר חופשי,"}, {"start": 381.67, "end": 382.77, "text": "ללא מגבלות רבות,"}, {"start": 383.53, "end": 388.81, "text": "על מנת לקדם את כל האתגרים שציינתי שאנחנו עומדים בפניהם."}, {"start": 390.23, "end": 393.79, "text": "אני יכול לומר לכם, כשר ביטחון, חזרתי כעת מביקור ביוון,"}, {"start": 394.95, "end": 397.05, "text": "לא מרבה לנסוע, אבל היתה נסיעה חשובה,"}, {"start": 399.07, "end": 402.89, "text": "וראיתי את ההערכה הרבה שיש שם,"}, {"start": 403.69, "end": 406.85, "text": "וכך בביקורים שמתקיימים כאן,"}, {"start": 407.83, "end": 409.69, "text": "של ראשי מערכות ביטחון בעולם,"}, {"start": 410.45, "end": 412.25, "text": "וגם בשיחות שאני מקיים אתן,"}, {"start": 412.97, "end": 414.23, "text": "אני רואה את ההערכה העצומה"}, {"start": 415.05, "end": 416.73, "text": "ליכולות שמדינת ישראל פיתחה."}, {"start": 418.25, "end": 420.37, "text": "וכמו שאמרתי, החברות הממשלתיות"}, {"start": 421.25, "end": 424.15, "text": "בעניין הזה היו במוקד"}, {"start": 425.37, "end": 428.67, "text": "העשייה והשגת הישגים בלתי הרגילים,"}, {"start": 429.53, "end": 430.23, "text": "שגם עכשיו"}, {"start": 431.79, "end": 434.53, "text": "היעדים הם יעדים מאוד מאתגרים,"}, {"start": 435.19, "end": 437.69, "text": "שיציבו אותנו בקדמת היכולות בעולם."}, {"start": 438.69, "end": 440.97, "text": "נושא שסימנו,"}, {"start": 441.81, "end": 442.75, "text": "ואני באופן אישי"}, {"start": 443.71, "end": 448.01, "text": "רואה אותו כחשוב מאוד, הוא קיים ברקע הדברים,"}, {"start": 448.89, "end": 449.35, "text": "עוסקים בו,"}, {"start": 450.23, "end": 454.13, "text": "אבל אני רואה אותו כנושא שחשוב לקדם אותו באופן"}, {"start": 455.97, "end": 459.13, "text": "דומה אבל שונה לחלוטין מאשר עד עכשיו"}, {"start": 459.75, "end": 462.49, "text": "לנושא החלל והיכולת"}, {"start": 463.21, "end": 464.01, "text": "הביטחונית בחלל."}, {"start": 464.53, "end": 468.81, "text": "כאשר עמדתי ובדקתי,"}, {"start": 469.45, "end": 470.33, "text": "תוך כדי שיח"}, {"start": 471.53, "end": 474.37, "text": "עם החברות עצמן, שיש בהן יכולות כאלה,"}, {"start": 475.35, "end": 478.83, "text": "עם מפאד וכל מי שעוסק בתחומים האלה ומילא את החלל,"}, {"start": 479.59, "end": 480.45, "text": "משרד הביטחון,"}, {"start": 481.81, "end": 487.79, "text": "אז ראיתי שכל פעם נושא החלל עלה מדרגה"}, {"start": 489.09, "end": 492.87, "text": "על רקע אירועים שקרו, שקשורים למדינת ישראל,"}, {"start": 493.79, "end": 496.91, "text": "בעיקר למגבלות גודלה והיקפה."}, {"start": 500.97, "end": 502.15, "text": "נקודה אחת מכריעה"}, {"start": 503.29, "end": 507.83, "text": "של כניסה לחלל ומיסוד הנושא הייתה לא במקרה,"}, {"start": 508.19, "end": 508.89, "text": "עד כמה שאני מבין,"}, {"start": 509.23, "end": 510.89, "text": "שמנחם בגין היה שר הביטחון,"}, {"start": 512.01, "end": 514.15, "text": "אבל זה היה ערב הנסיגה הישראלית מסיני."}, {"start": 515.29, "end": 517.57, "text": "כאשר אתה הולך לוותר על שטח כל כך גדול,"}, {"start": 518.63, "end": 520.87, "text": "אתה מבין את מה שברור,"}, {"start": 521.85, "end": 522.59, "text": "שהיתרון שלנו"}, {"start": 523.53, "end": 524.11, "text": "הוא לא בשטח"}, {"start": 525.15, "end": 526.59, "text": "ולא בהיקף האוכלוסייה,"}, {"start": 527.49, "end": 529.33, "text": "היתרון הוא במוח וביכולות."}, {"start": 530.47, "end": 531.13, "text": "וגם עכשיו,"}, {"start": 532.35, "end": 533.41, "text": "על רקע הלקחים"}, {"start": 534.47, "end": 535.63, "text": "מהמערכה הזאת,"}, {"start": 536.45, "end": 537.39, "text": "מלחמת הטילים הזאת,"}, {"start": 538.51, "end": 539.57, "text": "מגבלות השטח,"}, {"start": 540.91, "end": 543.17, "text": "מגבלות היקף האוכלוסייה, גודל הצבא,"}, {"start": 544.63, "end": 545.35, "text": "ברור לי לחלוטין"}, {"start": 546.81, "end": 547.35, "text": "שהיעד"}, {"start": 548.25, "end": 550.41, "text": "שאותו התוויתי למערכת הביטחון"}, {"start": 551.27, "end": 552.45, "text": "ולחברות שעוסקות"}, {"start": 553.05, "end": 554.71, "text": "ולכלל העוסקים בתחום הזה,"}, {"start": 555.91, "end": 557.99, "text": "זה יעד של להיות אחת"}, {"start": 558.77, "end": 560.83, "text": "משלוש המדינות המובילות בעולם"}, {"start": 561.75, "end": 564.43, "text": "בתחום החלל ובתחום הביטחון בחלל."}, {"start": 566.07, "end": 569.63, "text": "לא אמרתי מקום רביעי אחרי שלוש המעצמות"}, {"start": 570.81, "end": 572.41, "text": "ולא אמרתי מקום שלישי."}, {"start": 573.29, "end": 574.57, "text": "אמרתי אחת מהשלוש,"}, {"start": 575.63, "end": 579.29, "text": "כאשר היכולת צריכה להיות בהתייצבות בחלל,"}, {"start": 580.17, "end": 582.69, "text": "בהגנה על מה ששמים בחלל,"}, {"start": 583.63, "end": 587.97, "text": "בהגנה על מדינת ישראל ובתקיפה מהחלל."}, {"start": 589.03, "end": 590.73, "text": "אלה היעדים שהוצבו."}, {"start": 591.77, "end": 593.15, "text": "זה דומה לכך"}, {"start": 594.55, "end": 595.77, "text": "שכאשר הוחלט,"}, {"start": 597.13, "end": 597.67, "text": "החלטה דרמטית,"}, {"start": 598.41, "end": 599.87, "text": "שישראל צריכה יכולת הגנה,"}, {"start": 601.27, "end": 602.99, "text": "הגנה מפני טילים,"}, {"start": 603.99, "end": 605.25, "text": "בעיקר אחרי מלחמת המפרץ,"}, {"start": 607.33, "end": 609.01, "text": "נעשה כאן מאמץ משמעותי"}, {"start": 609.77, "end": 612.91, "text": "שהביא את ישראל להיות המדינה המובילה בעולם ביכולות האלה,"}, {"start": 613.93, "end": 615.77, "text": "וכך צריך להיות, ועוד יותר,"}, {"start": 616.57, "end": 617.13, "text": "בתחום החלל."}, {"start": 618.05, "end": 619.89, "text": "אני קורא כאן, כמובן, לחברות,"}, {"start": 621.05, "end": 623.51, "text": "כמובן, של משרד הביטחון עצמו, צה״ל,"}, {"start": 624.55, "end": 627.57, "text": "אני קורא לכולם, כל מי שעוסק כאן בדברים שקשורים,"}, {"start": 629.65, "end": 631.25, "text": "וכמעט כל דבר קשור לזה,"}, {"start": 631.93, "end": 634.03, "text": "להתגייס ולהירתם לנושא הזה."}, {"start": 635.01, "end": 635.97, "text": "אני חושב שהיעד"}, {"start": 636.95, "end": 637.99, "text": "הוא להציב יכולות ישראליות,"}, {"start": 639.53, "end": 641.03, "text": "שיאפשרו לנו להתמודד,"}, {"start": 641.71, "end": 644.33, "text": "להרתיע ולהתמודד"}, {"start": 645.09, "end": 647.67, "text": "מול היקפים רחבים יותר של איומים,"}, {"start": 648.63, "end": 649.97, "text": "כי בסופו של דבר,"}, {"start": 651.39, "end": 656.13, "text": "בתחום הזה של האיומים אין כמעט גריעה של איומים."}, {"start": 656.89, "end": 657.45, "text": "אתה יכול להחליש,"}, {"start": 658.65, "end": 662.49, "text": "אתה יכול להתחזק על חשבון, למצוא פתרונות,"}, {"start": 663.59, "end": 663.93, "text": "אבל יש"}, {"start": 664.47, "end": 667.27, "text": "הצטברות של איומים והצטרפות של איומים."}, {"start": 669.05, "end": 670.19, "text": "ולא נפרט כאן,"}, {"start": 671.13, "end": 672.37, "text": "אבל בהחלט ביניהן"}, {"start": 673.07, "end": 674.97, "text": "יכולות להיות מדינות"}, {"start": 676.47, "end": 678.15, "text": "בעלי היקפי אוכלוסייה גדולים,"}, {"start": 679.41, "end": 681.25, "text": "בעלי שטח גדול מאוד,"}, {"start": 682.25, "end": 687.11, "text": "ולכן בסופו של דבר אנחנו צריכים לנצל את היתרון,"}, {"start": 688.07, "end": 688.97, "text": "היתרון שיש לנו"}, {"start": 689.63, "end": 690.39, "text": "זה ביכולת,"}, {"start": 691.37, "end": 694.17, "text": "בחשיבה, בפיתוח, במקוריות,"}, {"start": 694.89, "end": 696.67, "text": "כמו שעשינו בתחומים אחרים,"}, {"start": 697.45, "end": 699.81, "text": "לקחת יכולות שכבר קיימות היום בתחום,"}, {"start": 700.53, "end": 708.33, "text": "להוסיף עליהן ולהציג את היעד הזה כדי שמדינת ישראל תהיה מעצמת חלל כחול-לבן,"}, {"start": 709.71, "end": 711.49, "text": "מלחמת כוכבים כחול-לבן."}, {"start": 712.47, "end": 714.01, "text": "זה היעד שבא בתוך"}, {"start": 714.97, "end": 716.47, "text": "כלל התוכנית,"}, {"start": 717.83, "end": 720.65, "text": "התוכנית האדירה הזאת"}, {"start": 721.37, "end": 722.49, "text": "שאנחנו הולכים להציב,"}, {"start": 723.45, "end": 724.85, "text": "בנוסף לכל הפיתוח"}, {"start": 724.93, "end": 727.33, "text": "שיש במדינת ישראל,"}, {"start": 728.27, "end": 729.73, "text": "של כל הגורמים הפרטיים,"}, {"start": 730.15, "end": 730.67, "text": "של כל המחקרים,"}, {"start": 731.77, "end": 732.49, "text": "של כל המייצרים,"}, {"start": 733.73, "end": 734.67, "text": "ואותן מדינות"}, {"start": 735.51, "end": 737.07, "text": "שנבחר אותן בקפילה רבה,"}, {"start": 737.95, "end": 740.07, "text": "שנחליט שאנחנו יכולים לשתף איתן פעולה"}, {"start": 740.87, "end": 743.15, "text": "בגלל האיכות והיכולות שלהן,"}, {"start": 744.27, "end": 745.47, "text": "בגלל האמינות שלהן בעינינו,"}, {"start": 746.65, "end": 749.93, "text": "בגלל הביטחון שלנו שאנחנו יכולים לפעול ביחד איתן,"}, {"start": 750.99, "end": 752.21, "text": "אנחנו בהחלט נרצה לעשות"}, {"start": 752.79, "end": 756.87, "text": "גם את זה וגם את מכלול הדברים וכל מה שאפשר מהם,"}, {"start": 757.61, "end": 758.97, "text": "גם כן תוך כדי שותפות."}, {"start": 759.81, "end": 761.23, "text": "אני יכול להזכיר כאן רק את גרמניה,"}, {"start": 762.07, "end": 767.23, "text": "שקונה וגם תפעל בייצור משותף,"}, {"start": 767.93, "end": 768.81, "text": "שיחזק גם את היכולות כאן,"}, {"start": 769.99, "end": 771.89, "text": "ולא אוסיף וארחיב בשאר המדינות"}, {"start": 772.67, "end": 774.73, "text": "שקיימות ורוצות ומעוניינות."}, {"start": 775.75, "end": 776.17, "text": "העשור הזה"}, {"start": 776.93, "end": 778.75, "text": "הולך להיות עשור של בנייה אדירה,"}, {"start": 779.61, "end": 780.21, "text": "פיתוח אדיר,"}, {"start": 781.21, "end": 782.99, "text": "ואני בהחלט רואה את"}, {"start": 783.97, "end": 785.01, "text": "החברות הביטחוניות,"}, {"start": 785.89, "end": 786.59, "text": "שר ביטחון,"}, {"start": 787.43, "end": 789.41, "text": "אבל אני רואה גם הרבה חברות אחרות"}, {"start": 790.07, "end": 791.95, "text": "שיכולות להיות שותפות לנושא הזה."}, {"start": 792.55, "end": 796.49, "text": "אני רוצה רק לגעת ולומר,"}, {"start": 797.69, "end": 799.11, "text": "אנחנו נמצאים בשבע חזיתות,"}, {"start": 800.17, "end": 800.61, "text": "פעלנו,"}, {"start": 801.93, "end": 803.87, "text": "אנחנו נפעל על מנת לוודא"}, {"start": 804.63, "end": 806.63, "text": "שהאירוע הנורא שקרה ב-7 באוקטובר,"}, {"start": 809.11, "end": 810.07, "text": "המכה העצומה"}, {"start": 811.21, "end": 811.99, "text": "שספגנו"}, {"start": 812.97, "end": 813.49, "text": "לא יחזור,"}, {"start": 814.35, "end": 816.37, "text": "והלקחים מופקים והמדיניות משתנה,"}, {"start": 817.69, "end": 819.25, "text": "והיום, כתוצאה מהחלטות"}, {"start": 820.13, "end": 820.97, "text": "ומהיכולת"}, {"start": 821.63, "end": 822.91, "text": "הגדולה של מדינת ישראל,"}, {"start": 824.09, "end": 826.15, "text": "ובעיקר מההקרבה,"}, {"start": 826.91, "end": 827.63, "text": "מהמסירות,"}, {"start": 828.33, "end": 829.07, "text": "מהנחישות"}, {"start": 829.79, "end": 832.81, "text": "של החיילים והחיילות שלנו בסדיר,"}, {"start": 833.53, "end": 834.05, "text": "בקבע,"}, {"start": 834.63, "end": 835.25, "text": "במילואים,"}, {"start": 835.93, "end": 837.63, "text": "שנושאים על כתפיהם"}, {"start": 838.37, "end": 839.73, "text": "את נטל הביטחון"}, {"start": 841.03, "end": 844.23, "text": "בדבר שהוא חסר תקדים בקנה מידה עולמי,"}, {"start": 845.05, "end": 852.61, "text": "כשמדינות מתקשות להקים צבאות או להרחיב צבאות או לעשות שירות חובה או לגייס,"}, {"start": 853.31, "end": 855.07, "text": "כאן רואים מאות אלפי חיילי מילואים"}, {"start": 855.63, "end": 859.01, "text": "שמצטרפים לאנשי הקבע וחיילי הסדיר ומשרתים,"}, {"start": 859.35, "end": 866.03, "text": "והודות לזה אנחנו יכולים לקבל את ההחלטות כפי שקיבלנו וכפי שנמשיך לקבל."}, {"start": 866.73, "end": 872.15, "text": "לא נאפשר יותר לאיומים להצטבר מול מדינת ישראל בניגוד למה שהיה קודם."}, {"start": 873.39, "end": 873.97, "text": "לא נאפשר"}, {"start": 874.79, "end": 877.51, "text": "יותר לארגונים ג'יהאדיסטיים וכוחות ג'יהאדיסטיים"}, {"start": 878.31, "end": 879.19, "text": "להיות סמוכים"}, {"start": 880.21, "end": 881.43, "text": "לגבולות מדינת ישראל,"}, {"start": 882.51, "end": 883.97, "text": "להם על התושבים ועל היישובים."}, {"start": 884.95, "end": 887.31, "text": "המדיניות שלנו, של הגנת הגבולות והיישובים,"}, {"start": 888.11, "end": 889.31, "text": "בלבנון, בסוריה,"}, {"start": 890.33, "end": 890.75, "text": "בעזה"}, {"start": 891.39, "end": 893.45, "text": "ובכל מקום, היא מדיניות ברורה."}, {"start": 894.41, "end": 895.41, "text": "צהל חוצץ."}, {"start": 896.57, "end": 897.35, "text": "מתוך השטח"}, {"start": 898.13, "end": 899.13, "text": "של הצד השני,"}, {"start": 900.35, "end": 901.95, "text": "בין גופים ג'יהאדיסטיים"}, {"start": 902.77, "end": 903.97, "text": "לבין היישובים"}, {"start": 905.05, "end": 905.91, "text": "והתושבים של מדינת ישראל."}, {"start": 907.21, "end": 908.41, "text": "כך מעל הרי הלבנון,"}, {"start": 909.21, "end": 910.65, "text": "שצהל נמצא ברצועת ביטחון,"}, {"start": 911.59, "end": 912.33, "text": "כך בסוריה,"}, {"start": 913.21, "end": 914.29, "text": "שצהל נמצא"}, {"start": 915.15, "end": 917.03, "text": "בפסגת החרמון ובאזור ביטחון,"}, {"start": 918.07, "end": 918.77, "text": "ולא נזוז"}, {"start": 919.47, "end": 922.21, "text": "מהמקומות האלה באופן חד-משמעי,"}, {"start": 922.87, "end": 924.49, "text": "משום שאנחנו לא סומכים"}, {"start": 925.33, "end": 926.85, "text": "על אף גורם חיצוני,"}, {"start": 927.99, "end": 931.73, "text": "או מהצד השני שהוא יארוב לביטחוננו,"}, {"start": 932.53, "end": 933.35, "text": "כי ראינו בדיוק את המשמעות."}, {"start": 934.39, "end": 935.11, "text": "וגם בעזה,"}, {"start": 935.87, "end": 936.97, "text": "אחרי שברוך השם"}, {"start": 937.89, "end": 939.25, "text": "שחררנו את כל החטופים החיים,"}, {"start": 940.37, "end": 941.63, "text": "והחטופים החללים,"}, {"start": 942.27, "end": 943.83, "text": "ורן גבילי, גיבור ישראל,"}, {"start": 944.47, "end": 945.21, "text": "נכונו לברכה,"}, {"start": 945.71, "end": 946.21, "text": "לא נרפה"}, {"start": 946.73, "end": 950.67, "text": "עד שנחזיר אותו גם כן למדינת ישראל, לקבר ישראל."}, {"start": 951.57, "end": 952.51, "text": "אחרי שעשינו את זה"}, {"start": 953.27, "end": 954.25, "text": "ואנחנו נמצאים"}, {"start": 954.93, "end": 955.77, "text": "בתוך עזה"}, {"start": 956.77, "end": 958.89, "text": "ושומרים על הביטחון בקו הצהוב,"}, {"start": 959.91, "end": 960.67, "text": "במוצבים,"}, {"start": 961.31, "end": 963.17, "text": "שומרים על החיילים, שומרים על היישובים,"}, {"start": 964.47, "end": 968.65, "text": "אנחנו עומדים על פירוק ה'חמאס' מנשקו ועל פירוז עזה ממנהרות"}, {"start": 969.47, "end": 971.31, "text": "וכל תשתיות הטרור,"}, {"start": 971.95, "end": 973.51, "text": "וכך הדבר הזה יהיה,"}, {"start": 974.15, "end": 978.29, "text": "או כתוצאה מהפעילות הבין-לאומית או כתוצאה מפעילות שלנו."}, {"start": 979.19, "end": 979.87, "text": "אבל בכל מקרה,"}, {"start": 981.25, "end": 982.97, "text": "בכל מקרה, גם אחרי שזה יהיה,"}, {"start": 983.17, "end": 987.07, "text": "צה״ל יישאר באזור ביטחון,"}, {"start": 987.83, "end": 988.61, "text": "ברצועת ביטחון,"}, {"start": 989.25, "end": 989.95, "text": "סביב עזה,"}, {"start": 990.71, "end": 991.45, "text": "בתוך עזה,"}, {"start": 991.79, "end": 997.11, "text": "במקומות שולטים כדי להגן על היישובים ועל האזרחים של מדינת ישראל."}, {"start": 998.17, "end": 999.23, "text": "זו התפיסה שלנו,"}, {"start": 999.81, "end": 1000.73, "text": "את זה אנחנו עושים,"}, {"start": 1001.45, "end": 1002.41, "text": "ואנחנו מגובים,"}, {"start": 1003.19, "end": 1005.09, "text": "כמו שאמרתי, על-ידי הגבורה הגדולה"}, {"start": 1005.65, "end": 1006.51, "text": "של החיילים,"}, {"start": 1007.25, "end": 1009.67, "text": "ואנחנו מגובים על-ידי היכולות,"}, {"start": 1010.65, "end": 1012.07, "text": "היכולות של מדינת ישראל,"}, {"start": 1012.71, "end": 1014.25, "text": "יכולות ביטחוניות, כלכליות,"}, {"start": 1015.01, "end": 1015.39, "text": "ששזורות"}, {"start": 1015.95, "end": 1016.55, "text": "זו בזו."}, {"start": 1017.15, "end": 1018.09, "text": "ואני מאחל לכם,"}, {"start": 1018.91, "end": 1020.99, "text": "כאחד הקטרים המרכזיים במשק,"}, {"start": 1022.21, "end": 1025.59, "text": "לצד כל המגזרים הפרטיים המובילים,"}, {"start": 1026.49, "end": 1028.31, "text": "מאחל לכם המשך עבודה פרייה,"}, {"start": 1029.21, "end": 1030.27, "text": "מאחל לכם להצליח."}, {"start": 1031.19, "end": 1033.37, "text": "אני מברך כאן, יש גם נציגי ועדי עובדים."}, {"start": 1034.21, "end": 1035.45, "text": "אתם יודעים, עשיתי הרבה רפורמות."}, {"start": 1036.51, "end": 1037.15, "text": "בזמנו,"}, {"start": 1038.09, "end": 1041.11, "text": "חוץ ממקום אחד, זה לא היה בהסכמת הוועדים."}, {"start": 1042.37, "end": 1044.45, "text": "המקום היחידי שנתן לי את ברכתו"}, {"start": 1045.45, "end": 1046.97, "text": "היתה רשות שדות התעופה,"}, {"start": 1047.77, "end": 1048.33, "text": "כאשר"}, {"start": 1049.23, "end": 1051.53, "text": "יושב-ראש הוועד אמר, נעשה ונשמר,"}, {"start": 1052.39, "end": 1054.21, "text": "אתה רוצה שמים פתוחים, תחרות,"}, {"start": 1054.89, "end": 1055.55, "text": "תהיה תחרות,"}, {"start": 1056.31, "end": 1057.91, "text": "בסופו של דבר הוא דאג גם לעובדים."}, {"start": 1058.87, "end": 1059.93, "text": "נאבקתי בנמלים,"}, {"start": 1060.83, "end": 1062.03, "text": "נאבקתי ברכבות,"}, {"start": 1063.07, "end": 1068.01, "text": "נאבקתי במגוון שלם של דברים, שלא נחזור."}, {"start": 1068.95, "end": 1071.91, "text": "אבל דבר אחד משמח אותי היום,"}, {"start": 1072.45, "end": 1074.97, "text": "כי כפי שצפיתי כבר אז,"}, {"start": 1076.09, "end": 1076.49, "text": "התחרות"}, {"start": 1077.35, "end": 1078.39, "text": "הביאה להרחבה,"}, {"start": 1079.35, "end": 1080.27, "text": "הביאה לתוספת עובדים,"}, {"start": 1081.21, "end": 1081.97, "text": "תוספת פעילות."}, {"start": 1083.01, "end": 1083.89, "text": "לא פוטרו עובדים,"}, {"start": 1084.53, "end": 1086.67, "text": "התבצעו עובדים, אבל תוך כדי תחרות,"}, {"start": 1087.31, "end": 1089.67, "text": "עם כל הגורמים שהצטרפו למערכת הזאת."}, {"start": 1090.25, "end": 1094.05, "text": "וזו המדיניות הנכונה שאני רואה גם כשאני מדבר אתכם כאן,"}, {"start": 1094.97, "end": 1098.19, "text": "לקדם כל רפורמה שמביאה תחרות,"}, {"start": 1098.87, "end": 1102.71, "text": "מביאה התייעלות תוך שמירה על החברות הממשלתיות,"}, {"start": 1103.61, "end": 1105.95, "text": "אלא אם כן יש תהליך של הפרטה בהסכמה,"}, {"start": 1106.99, "end": 1108.71, "text": "שזה דבר גם כן לגיטימי."}, {"start": 1109.25, "end": 1112.39, "text": "מבחינתי, התחרות היתה יותר חשובה מההפרטה,"}, {"start": 1113.37, "end": 1115.71, "text": "כי התחרות הובילה לאותן תוצאות."}, {"start": 1116.39, "end": 1117.61, "text": "תראו את היקף הפעילות בנמלים,"}, {"start": 1119.47, "end": 1122.41, "text": "תראו, בשמים הפתוחים, ביום טוב, שהייתי עד 2019,"}, {"start": 1123.41, "end": 1125.95, "text": "עברו 25 מיליון נוסעים בנתב״ג."}, {"start": 1127.01, "end": 1128.05, "text": "אני מקווה שזה עוד יחזור."}, {"start": 1128.71, "end": 1129.35, "text": "זה התרחב."}, {"start": 1130.07, "end": 1132.01, "text": "הרחבות הכפילו את עצמן, הרכבות,"}, {"start": 1132.87, "end": 1133.09, "text": "הכבישים"}, {"start": 1133.73, "end": 1134.31, "text": "וכל הדברים."}, {"start": 1135.05, "end": 1138.07, "text": "אז אני מאחל לכם המשך עבודה פרייה והצלחה,"}, {"start": 1139.81, "end": 1144.37, "text": "כלכלה חזקה וביטחון חזק במדינת ישראל. תודה רבה לכם."}]}, {"video_id": "CrmwoJayd3o", "url": "https://www.youtube.com/watch?v=CrmwoJayd3o", "title": "יודעים איך ישראל כץ עשה דיאטה?", "channel": "ירון זליכה - Yaron Zelekha", "published_at": "2025-10-11T17:30:03Z", "person_id": 468, "mk_name": "ישראל כץ", "duration_sec": 68.7, "engine": "ivrit-ai/whisper-large-v3-turbo-ct2", "transcribed_at": "2026-06-27T00:20:27.067097+00:00", "segments": [{"start": 0.0, "end": 2.38, "text": "במשך החצי שנה שעבדתי על הוועדה,"}, {"start": 3.34, "end": 5.72, "text": "תבין, בשוק הרכב יש כל כך הרבה חוסר תחרות,"}, {"start": 6.16, "end": 8.12, "text": "שאתה צריך, אפילו אני, שאני מומחה,"}, {"start": 8.46, "end": 10.94, "text": "צריך חצי שנה בשביל לפרק את כל הכשלים."}, {"start": 11.64, "end": 12.48, "text": "בקיצור ולעניין,"}, {"start": 12.84, "end": 14.32, "text": "עברו חצי שנה, בינתיים,"}, {"start": 14.66, "end": 15.96, "text": "כחלון כיכב בסקרים."}, {"start": 16.34, "end": 16.44, "text": "כן."}, {"start": 16.86, "end": 18.0, "text": "וזה גרם לביבי"}, {"start": 19.66, "end": 20.78, "text": "להפוך אותו לאויב."}, {"start": 21.58, "end": 24.08, "text": "אם כחלון מככב בסקרים, הוא הופך להיות אויב."}, {"start": 24.62, "end": 25.24, "text": "בקיצור,"}, {"start": 25.78, "end": 26.64, "text": "שר האוצר,"}, {"start": 27.1, "end": 29.76, "text": "סליחה, נתניהו עשה לכחלון כפד ראשו,"}, {"start": 30.2, "end": 37.52, "text": "אתם זוכרים שהוא כרש מהפוליטיקה? כן. ופתאום ישראל כץ אומר, רגע, אם הזליך הזה יבוא לי עם רפורמה אמיתית, שתוריד פה את מחירי הרכבים,"}, {"start": 38.18, "end": 41.34, "text": "אני אעלה בסקרים ונתניהו עושה לי כפה את ראשו."}, {"start": 41.76, "end": 42.96, "text": "בקיצור, אני מגיע אליו,"}, {"start": 43.92, "end": 44.92, "text": "אומר לו, הנה הדוח."}, {"start": 45.88, "end": 48.24, "text": "עכשיו הוא יושב עם ה-150 קילו שלו,"}, {"start": 48.86, "end": 49.84, "text": "מתחיל לקרוא את הדוח,"}, {"start": 50.56, "end": 52.24, "text": "ואני רואה אותו לנגד עיניי,"}, {"start": 52.62, "end": 55.88, "text": "מתחיל להתכווץ ולרזוד ולרזוד ולרזוד."}, {"start": 56.24, "end": 59.82, "text": "עכשיו, אילולא משכתי לו את הדוח מהידיים אחרי 20 דקות,"}, {"start": 60.2, "end": 62.04, "text": "אני מודיע לך, הוא היה יורד ל-20 קילו."}, {"start": 63.88, "end": 68.36, "text": "עכשיו, צחוק צחוק, מתוך ה-52 המלצות, הוא יישם רק שניים."}]}]}